{"comments":["C罗未必有我焦虑这句话太真实了","场上的人还能跑屏幕外的人只能等","41岁还在世界杯拼命","他已经把能给的都给了","补时被绝杀那一下太残酷了","没给葡萄牙留下追平的时间","他站在场上沉默的样子我哭了","少年到队长走了好长的路","从不服输的眼神到赛后落泪的背影","意难平但真的拼过了","球迷焦虑是因为真的在乎","他平静接受也是因为真的拼过","他陪很多人的青春走了很久","看台上的传奇场上的他","时间终究没有放过任何人","葡萄牙停在这里好不甘心","但C罗的分量不会因为一个比分减少","他站在那里本身就是传奇","最后一舞结束得太突然","两种在乎的方式都让人破防","他带走了很多人的青春记忆","41岁的告别配得上所有掌声","虽然不是用胜利收尾","但问心无愧就够了","你的焦虑比我们少但你的重量比谁都大"],"assignments":{"device-jmot8pqw":"没给葡萄牙留下追平的时间","device-9car5ewb":"看台上的传奇场上的他","device-am0yanyt":"41岁的告别配得上所有掌声","device-a5hsf08i":"你的焦虑比我们少但你的重量比谁都大","dh3xk8u":"最后一舞结束得太突然"}}